keplergl_quickvis
