Metadata-Version: 2.1
Name: keplergl-quickvis
Version: 0.2.0
Summary: Description 
Home-page: https://github.com/kylebarron/keplergl_quickvis
Author: Kyle Barron
Author-email: kylebarron2@gmail.com
License: MIT license
Keywords: keplergl,mapbox
Platform: UNKNOWN
Classifier: Development Status :: 4 - Beta
Classifier: Intended Audience :: Developers
Classifier: License :: OSI Approved :: MIT License
Classifier: Natural Language :: English
Classifier: Programming Language :: Python :: 3
Classifier: Programming Language :: Python :: 3.5
Classifier: Programming Language :: Python :: 3.6
Classifier: Programming Language :: Python :: 3.7
Classifier: Programming Language :: Python :: 3.8
Requires-Python: >=3.5
